llama_index/packs/vanna/__init__.py
llama_index/packs/vanna/base.py
llama_index_packs_vanna-0.3.0.dist-info/METADATA
llama_index_packs_vanna-0.3.0.dist-info/WHEEL
llama_index_packs_vanna-0.3.0.dist-info/RECORD
